{"minVersion":"0.1","headerImage":"https://dollazyt.github.io/DollazYT/assets/SkylineBanner.png","tintColor":"#2ECC71","tabs":[{"tabname":"Details","views":[{"class":"DepictionScreenshotsView","screenshots":[{"url":"https://dollazyt.github.io/DollazYT/assets/screenshot/aa.png","accessibilityText":"Screenshot"},{"url":"https://dollazyt.github.io/DollazYT/assets/screenshot/aa.png","accessibilityText":"Screenshot"},{"url":"https://dollazyt.github.io/DollazYT/assets/screenshot/aa.png","accessibilityText":"Screenshot"}],"itemCornerRadius":8,"itemSize":"{100,200}"},{"markdown":"ModMenuX - KissThaGameGoodbye - Skyline \n-----------------------------------\n\nThis package contains a menu for bcw.\n\nDisclaimer\n----\nI take no responsibility of anything that you do with this mod, remember that cheating eventually results in a ban. That is not our fault nor problem. Enjoy!\n\n#### Do not share deb to anyone, share the repo instead. This makes it easier to push updates for everyone. Thank you. (This Won't Ban)\n\nFeatures\n----\n\n- Speed\n\n- Jump\n\n- No Fall Damage\n\n- Unlimited Ammo\n\n- One Shot\n\n- Rapid Fire\n\n- No Reload\n\n- Super Spread\n\n- Wobble Lag\n\n- Unlimited JP\n\n- JP Speed\n\n- Nailgun Silent Aim\n\n- Melee Silent Aim\n\n- TACTICAL NUKE\n\n- Godmode\n\n- Invisibility\n\n- Akimbo\n\n- Big Enemies\n\n- Big Player\n\n- Normal Players\n\n- Masskill\n\n- Always Shoot\n\n- Chams\n\n- Grand Theft Auto\n\n- Semi Fly\n\n- Visually Freeze Server\n\n- No Weapon Charge\n\n- Bombs Dont Explode\n\n- VIP\n\n- Unlock All\n\n- Free Store\n\n- Stupid AI\n\n- Stars\n\n- Increased FOV\n\n- Fall Off Bike\n\n- Never Fall Off Bike\n\n- No Vehicle Cooldown\n\n- Camber\n\n- Engine Off\n\n- Can Exit Titan\n\n- Spawn titan Anywhere\n\n- Titan SPD\n\n- Titan JP\n\n- Unlimited Titan Ammo\n\n- Titan Rapid Fire\n\n- Dont Die To Water\n\n\n","useSpacing":"true","class":"DepictionMarkdownView"},{"class":"DepictionSpacerView"},{"class":"DepictionHeaderView","title":"Information"},{"class":"DepictionTableTextView","title":"Developer","text":"DollazYT"},{"class":"DepictionTableTextView","title":"Version","text":"7.2.2"},{"class":"DepictionTableTextView","title":"Compatibility","text":"iOS 11.0 to 14.7"},{"class":"DepictionTableTextView","title":"Section","text":"Theme"},{"class":"DepictionSpacerView"},{"class":"DepictionTableButtonView","title":"Contact Support","action":"https://platinmods.com/threads/spotult-v8-5-65-mod-ipa.130186/","openExternal":"true","tintColor":"#2ECC71"},{"class":"DepictionLabelView","text":"Mod Menu \u2013 Updated 2021-06-12","textColor":"#999999","fontSize":"10.0","alignment":1}],"class":"DepictionStackView"},{"tabname":"Changelog","views":[{"class":"DepictionMarkdownView","markdown":"#### Version 1.0\n\n\t\n\u2022 Initial Release"},{"class":"DepictionLabelView","text":"Mod Menu \u2013 Updated 2021-06-12","textColor":"#999999","fontSize":"10.0","alignment":1}],"class":"DepictionStackView"}],"class":"DepictionTabView"}